{
  "Version": "2012-10-17",
  "Statement": [
    {
      "Sid": "AllowCloudWatchLogsWrite",
      "Effect": "Allow",
      "Action": [
        "logs:CreateLogGroup",
        "logs:CreateLogStream",
        "logs:PutLogEvents",
        "logs:DescribeLogStreams"
      ],
      "Resource": "arn:aws:logs:*:*:*"
    },
    {
      "Sid": "AllowSSMParameterReadScoped",
      "Effect": "Allow",
      "Action": [
        "ssm:GetParameter",
        "ssm:GetParameters",
        "ssm:GetParametersByPath"
      ],
      "Resource": "arn:aws:ssm:REGION:ACCOUNT_ID:parameter/capitol/*"
    },
    {
      "Sid": "AllowSecretsManagerReadScoped",
      "Effect": "Allow",
      "Action": [
        "secretsmanager:GetSecretValue",
        "secretsmanager:DescribeSecret"
      ],
      "Resource": "arn:aws:secretsmanager:REGION:ACCOUNT_ID:secret:capitol/*"
    },
    {
      "Sid": "OptionalS3ReadWriteBucket",
      "Effect": "Allow",
      "Action": [
        "s3:ListBucket",
        "s3:GetObject",
        "s3:PutObject"
      ],
      "Resource": [
        "arn:aws:s3:::CAPITOL_BUCKET_NAME",
        "arn:aws:s3:::CAPITOL_BUCKET_NAME/*"
      ]
    }
  ]
}
